{
  "page": 10,
  "tags": [
    {
      "tag": "P",
      "text": "PROBLEM DEFINITION",
      "bbox": [
        189.72000122070312,
        61.56004333496094,
        323.9003601074219,
        70.92940521240234
      ],
      "size": 12.044972896575928,
      "bold": false,
      "region": null
    },
    {
      "tag": "P",
      "text": "Understanding the potential implication of the NPDES Storm Water Final Rules in promoting",
      "bbox": [
        24.1199951171875,
        107.28002166748047,
        471.1004333496094,
        121.6918716430664
      ],
      "size": 10.961950778961182,
      "bold": false,
      "region": null
    },
    {
      "tag": "P",
      "text": "the reduction of impervious surfaces through urban design requires the understanding storm",
      "bbox": [
        23.760040283203125,
        127.79996490478516,
        460.3399353027344,
        141.8518524169922
      ],
      "size": 11.041325569152832,
      "bold": false,
      "region": null
    },
    {
      "tag": "P",
      "text": "water runoff and its relationships to the hydrologic cycle and the environment.",
      "bbox": [
        23.4000244140625,
        148.31996154785156,
        395.53955078125,
        161.65110778808594
      ],
      "size": 10.824628829956055,
      "bold": false,
      "region": null
    },
    {
      "tag": "P",
      "text": "Storm Water Runoff",
      "bbox": [
        207.36004638671875,
        211.31993103027344,
        305.2597961425781,
        220.6892852783203
      ],
      "size": 10.269115924835205,
      "bold": false,
      "region": null
    },
    {
      "tag": "P",
      "text": "To understand the effects of impervious surface on the environment, the hydrologic cycle must",
      "bbox": [
        22.320037841796875,
        250.55992126464844,
        473.2601623535156,
        264.9721374511719
      ],
      "size": 10.953780174255371,
      "bold": false,
      "region": null
    },
    {
      "tag": "P",
      "text": "be understood. In urbanized communities the natural ground cover of roots, leaf litter, forests or",
      "bbox": [
        22.320037841796875,
        271.4399108886719,
        478.6201477050781,
        284.77105712890625
      ],
      "size": 10.598079681396484,
      "bold": false,
      "region": null
    },
    {
      "tag": "P",
      "text": "grasslands are replaced with impervious surfaces such as roadways, curbs and gutters, sidewalks,",
      "bbox": [
        21.96002197265625,
        291.95989990234375,
        482.69989013671875,
        306.0117492675781
      ],
      "size": 10.899600982666016,
      "bold": false,
      "region": null
    },
    {
      "tag": "P",
      "text": "roofs, parking lots and other hardened or compacted surfaces. Where once natural ground cover",
      "bbox": [
        21.600006103515625,
        312.4798889160156,
        480.500244140625,
        326.8921203613281
      ],
      "size": 11.309621810913086,
      "bold": false,
      "region": null
    },
    {
      "tag": "P",
      "text": "allowed rainfall to slowly percolate and infiltrate into aquifers, streams and lakes; rainfall",
      "bbox": [
        21.60003662109375,
        333.35986328125,
        446.81982421875,
        346.33135986328125
      ],
      "size": 10.182403564453125,
      "bold": false,
      "region": null
    },
    {
      "tag": "P",
      "text": "runs off the roadways, sidewalks, rooftops and other compacted surfaces disrupting the natural",
      "bbox": [
        21.240081787109375,
        353.8798522949219,
        470.74041748046875,
        367.93170166015625
      ],
      "size": 10.806243419647217,
      "bold": false,
      "region": null
    },
    {
      "tag": "P",
      "text": "hydrological cycle. Evapo-transpiration and underground interflow between the soil and bedrock,",
      "bbox": [
        21.240081787109375,
        374.0398254394531,
        484.060546875,
        388.0916748046875
      ],
      "size": 11.256950378417969,
      "bold": false,
      "region": null
    },
    {
      "tag": "P",
      "text": "and base flow within an aquifer are greatly reduced with impervious surfaces (Fig. 1).",
      "bbox": [
        20.88006591796875,
        394.9197998046875,
        428.1400146484375,
        409.33203125
      ],
      "size": 11.063496589660645,
      "bold": false,
      "region": null
    },
    {
      "tag": "P",
      "text": "now",
      "bbox": [
        451.080078125,
        339.11981201171875,
        471.0799560546875,
        345.2459411621094
      ],
      "size": 9.033252716064453,
      "bold": false,
      "region": null
    },
    {
      "tag": "P",
      "text": "Impervious surfaces are the hardened surfaces of urbanized communities that prevent natural",
      "bbox": [
        20.52008056640625,
        435.9598083496094,
        462.38037109375,
        450.3713073730469
      ],
      "size": 10.564105987548828,
      "bold": false,
      "region": null
    },
    {
      "tag": "P",
      "text": "infiltration into the soil during rainfall events. Rainfall is not absorbed through the hardened",
      "bbox": [
        20.52008056640625,
        457.1997985839844,
        458.34002685546875,
        470.89166259765625
      ],
      "size": 10.284443855285645,
      "bold": false,
      "region": null
    },
    {
      "tag": "P",
      "text": "surfaces, therefore impeding the removal of pollutants from runoff. Percolation",
      "bbox": [
        20.1600341796875,
        477.3597717285156,
        396.61993408203125,
        489.9723815917969
      ],
      "size": 10.741483688354492,
      "bold": false,
      "region": null
    },
    {
      "tag": "P",
      "text": "pollutants in the top six inches of soil (BASMAA 1999, 37). The runoff from these hardened",
      "bbox": [
        19.79998779296875,
        498.2397766113281,
        462.58050537109375,
        511.5705871582031
      ],
      "size": 10.770823955535889,
      "bold": false,
      "region": null
    },
    {
      "tag": "P",
      "text": "surfaces contains a multitude of pollutants and sediments compared to predevelopment runoff.",
      "bbox": [
        19.800018310546875,
        518.759765625,
        468.5798645019531,
        533.5320434570312
      ],
      "size": 11.083703994750977,
      "bold": false,
      "region": null
    },
    {
      "tag": "P",
      "text": "removes",
      "bbox": [
        400.6799621582031,
        483.47979736328125,
        439.6798400878906,
        489.6059265136719
      ],
      "size": 8.257964134216309,
      "bold": false,
      "region": null
    },
    {
      "tag": "P",
      "text": "4",
      "bbox": [
        247.67996215820312,
        728.27978515625,
        252.67991638183594,
        736.568115234375
      ],
      "size": 9.099414825439453,
      "bold": false,
      "region": {
        "cls": "figure",
        "score": 0.6689453125,
        "bbox": [
          247.50001525878906,
          725.7937622070312,
          254.30625915527344,
          739.40625
        ]
      }
    }
  ]
}